EGCI.py
__init__.py
EGCI-1.0.2.post1.dist-info/LICENSE
EGCI-1.0.2.post1.dist-info/METADATA
EGCI-1.0.2.post1.dist-info/WHEEL
EGCI-1.0.2.post1.dist-info/top_level.txt
EGCI-1.0.2.post1.dist-info/RECORD
