Metadata-Version: 2.1
Name: EGCI
Version: 1.0.2.post1
Summary: Ecoacoustic Global Complexity Index (EGCI)
Author-email: "Juan G. Colonna" <juancolonna@icomp.edu.ufam.br>
License: MIT License
Project-URL: repository, https://github.com/juancolonna/EGCI
Project-URL: scientific article, https://journals.plos.org/plosone/article?id=10.1371/journal.pone.0229425
Classifier: Programming Language :: Python :: 3
Classifier: License :: OSI Approved :: MIT License
Classifier: Operating System :: OS Independent
Requires-Python: >=3.10
License-File: LICENSE
Requires-Dist: numpy
Requires-Dist: scipy
Requires-Dist: statsmodels
